{
    "location": {
        "x": 599.0,
        "y": 0.0,
        "z": -235.0
    },
    "harvestableParticlePrefab": "MediumRoundFishParticles",
    "items": [ "deepsubmergence.fishclampster", "deepsubmergence.fishlampcrab" ],
    "startStock": 2,
    "maxStock": 6,
    "doesRestock": true,
    "usesTimeSpecificStock": false,
    "overrideDefaultDaySpecialChance": true,
    "overriddenDaytimeSpecialChance": 0.5,
    "overrideDefaultNightSpecialChance": true,
    "overriddenNighttimeSpecialChance": 0.5,
    "harvestDifficulty": "Easy",
}